source_code/session7/5_mealy_fsm/mealy_fsm.v
`timescale 1ns / 1ps
module mealy_fsm(
	input clk, rst_n, x, output z
);
  parameter A = 4'h1;
  parameter B = 4'h2;
  parameter C = 4'h3;
  parameter D = 4'h4;
  
  reg [3:0] state, next_state;
  always @(posedge clk or negedge rst_n) begin
    if(!rst_n) begin 
      state <= A;
    end
    else state <= next_state;
  end
  
  always @(state or x) begin
    case(state)
      A: begin
           if(x == 0) next_state = A;
           else       next_state = B;
         end
      B: begin
           if(x == 0) next_state = C;
           else       next_state = B;
         end
      C: begin
           if(x == 0) next_state = A;
           else       next_state = D;
         end
      D: begin
        if(x == 0) next_state = A; //This state only differs when compared with Mealy Overlaping Machine
           else       next_state = B;
         end
      default: next_state = A;
    endcase
  end
  assign z = (state == D) && (x == 0)? 1:0;
endmodule

source_code/session7/5_mealy_fsm/tb_mealy_fsm.v
`timescale 1ns/1ps
module tb_mealy_fsm;
  reg clk, rst_n, x;
  wire z;
  
  mealy_fsm uut(clk, rst_n, x, z);
  initial clk = 0;   
  always #2 clk = ~clk;
    
  initial begin
    x = 0;
    #1 rst_n = 0;
    #2 rst_n = 1;
    
    #3 x = 1;
    #4 x = 1;
    #4 x = 0;
    #4 x = 1;
    #4 x = 0;
    #4 x = 1;
    #4 x = 0;
    #4 x = 1;
    #4 x = 1;
    #4 x = 1;
    #4 x = 0;
    #4 x = 1;
    #4 x = 0;
    #4 x = 1;
    #4 x = 0;
    #10;
    $finish;
  end
  
  initial begin
    // Dump waves
    $dumpfile("dump.vcd");
    $dumpvars(0);
  end
endmodule

source_code/session7/3_mealy_fsm/dump.vcd
$date
   Tue May 12 22:45:57 2026
$end

$version
  2024.2.0
  $dumpfile ("dump.vcd") 
$end

$timescale
  1ps
$end

$scope module tb_mealy_fsm $end
$var reg 1 ! clk $end
$var reg 1 " rst_n $end
$var reg 1 # x $end
$var wire 1 $ z $end
$scope module uut $end
$var wire 1 % clk $end
$var wire 1 & rst_n $end
$var wire 1 ' x $end
$var wire 1 $ z $end
$var reg 4 ( state [3:0] $end
$var reg 4 ) next_state [3:0] $end
$upscope $end
$upscope $end
$enddefinitions $end

#0
$dumpvars
0!
x"
0#
x$
0%
x&
0'
bx (
b1 )
$end

#1000
0"
0$
0&
b1 (

#2000
1!
1%

#3000
1"
1&

#4000
0!
0%

#6000
1!
1#
1%
1'
b10 (
b10 )

#8000
0!
0%

#10000
1!
1%

#12000
0!
0%

#14000
1!
0#
1%
0'
b11 (
b1 )

#16000
0!
0%

#18000
1!
1#
1%
1'
b100 (
b10 )

#20000
0!
0%

#22000
1!
0#
0$
1%
0'
b1 (
b1 )

#24000
0!
0%

#26000
1!
1#
1%
1'
b10 (
b10 )

#28000
0!
0%

#30000
1!
0#
1%
0'
b11 (
b1 )

#32000
0!
0%

#34000
1!
1#
1%
1'
b100 (
b10 )

#36000
0!
0%

#38000
1!
1%
b10 (

#40000
0!
0%

#42000
1!
1%

#44000
0!
0%

#46000
1!
0#
1%
0'
b11 (
b1 )

#48000
0!
0%

#50000
1!
1#
1%
1'
b100 (
b10 )

#52000
0!
0%

#54000
1!
0#
0$
1%
0'
b1 (
b1 )

#56000
0!
0%

#58000
1!
1#
1%
1'
b10 (
b10 )

#60000
0!
0%

#62000
1!
0#
1%
0'
b11 (
b1 )

#64000
0!
0%

#66000
1!
1%
b1 (

